[
   {
      "name":"sea_1",
      "c_sea":[
         "sea_2",
         "sea_8",
         "sea_9"
      ],
      "c_land":[
         "eastern_canada"
      ],
      "x":"180",
      "y":"210"
   },
   {
      "name":"sea_2",
      "c_sea":[
         "sea_1",
         "sea_3",
         "sea_8"
      ],
      "c_land":[
         "united_kingdom"
      ],
      "x":"485",
      "y":"110"
   },
   {
      "name":"sea_3",
      "c_sea":[
         "sea_2",
         "sea_6",
         "sea_4"
      ],
      "c_land":[
         "united_kingdom",
         "norway"
      ],
      "x":"740",
      "y":"80"
   },
   {
      "name":"sea_4",
      "c_sea":[
         "sea_3"
      ],
      "c_land":[
         "norway",
         "karelia_ssr",
         "arcnangel"
      ],
      "x":"1133",
      "y":"52"
   },
   {
      "name":"sea_5",
      "c_sea":[
         "sea_6"
      ],
      "c_land":[
         "norway",
         "karelia_ssr",
         "eastern_europe",
         "germany",
         "western_europe"
      ],
      "x":"882",
      "y":"272"
   },
   {
      "name":"sea_6",
      "c_sea":[
         "sea_5",
         "sea_3",
         "sea_7"
      ],
      "c_land":[
         "united_kingdom",
         "norway",
         "western_europe"
      ],
      "x":"698",
      "y":"239"
   },
   {
      "name":"sea_7",
      "c_sea":[
         "sea_6",
         "sea_8"
      ],
      "c_land":[
         "united_kingdom",
         "western_europe"
      ],
      "x":"602",
      "y":"388"
   },
   {
      "name":"sea_8",
      "c_sea":[
         "sea_1",
         "sea_2",
         "sea_9",
         "sea_12",
         "sea_7"
      ],
      "c_land":[
         "united_kingdom"
      ],
      "x":"479",
      "y":"424"
   },
   {
      "name":"sea_9",
      "c_sea":[
         "sea_8",
         "sea_1",
         "sea_12",
         "sea_11",
         "sea_10"
      ],
      "c_land":[
         "eastern_canada"
      ],
      "x":"371",
      "y":"457"
   },
   {
      "name":"sea_10",
      "c_sea":[
         "sea_9",
         "sea_11",
         "sea_19"
      ],
      "c_land":[
         "eastern_united_states",
         "panama"
      ],
      "x":"252",
      "y":"576"
   },
   {
      "name":"sea_11",
      "c_sea":[
         "sea_12",
         "sea_18",
         "sea_19",
         "sea_10",
         "sea_9"
      ],
      "c_land":[
         
      ],
      "x":"360",
      "y":"679"
   },
   {
      "name":"sea_12",
      "c_sea":[
         "sea_11",
         "sea_9",
         "sea_8",
         "sea_7",
         "sea_18",
         "sea_17"
      ],
      "c_land":[
         
      ],
      "x":"477",
      "y":"728"
   },
   {
      "name":"sea_13",
      "c_sea":[
         "sea_12",
         "sea_14"
      ],
      "c_land":[
         "western_europe",
         "algeria"
      ],
      "x":"650",
      "y":"677"
   },
   {
      "name":"sea_14",
      "c_sea":[
         "sea_13",
         "sea_15",
         "sea_16"
      ],
      "c_land":[
         "southern_europe",
         "libya"
      ],
      "x":"889",
      "y":"719"
   },
   {
      "name":"sea_15",
      "c_sea":[
         "sea_14",
         "sea_16"
      ],
      "c_land":[
         "anglo_egypt",
         "balkans"
      ],
      "x":"1016",
      "y":"741"
   },
   {
      "name":"sea_16",
      "c_sea":[
         "sea_14",
         "sea_15"
      ],
      "c_land":[
         "balkans",
         "ukraine_ssr",
         "caucausus"
      ],
      "x":"1103",
      "y":"617"
   },
   {
      "name":"sea_17",
      "c_sea":[
         "sea_12",
         "sea_18",
         "sea_22",
         "sea_23"
      ],
      "c_land":[
         "french_west_africa"
      ],
      "x":"491",
      "y":"1029"
   },
   {
      "name":"sea_18",
      "c_sea":[
         "sea_11",
         "sea_12",
         "sea_19",
         "sea_22",
         "sea_17"
      ],
      "c_land":[
         "brazil"
      ],
      "x":"379",
      "y":"846"
   },
   {
      "name":"sea_19",
      "c_sea":[
         "sea_10",
         "sea_11",
         "sea_18"
      ],
      "c_land":[
         "panama",
         "west_indies"
      ],
      "x":"185",
      "y":"752"
   },
   {
      "name":"sea_20",
      "c_sea":[
         "sea_21",
         "sea_54",
         "sea_43"
      ],
      "c_land":[
         "panama"
      ],
      "x":"55",
      "y":"841"
   },
   {
      "name":"sea_21",
      "c_sea":[
         "sea_20",
         "sea_25",
         "sea_43",
         "sea_42"
      ],
      "c_land":[
         
      ],
      "x":"96",
      "y":"1080"
   },
   {
      "name":"sea_22",
      "c_sea":[
         "sea_18",
         "sea_17",
         "sea_23",
         "sea_24",
         "sea_25"
      ],
      "c_land":[
         "brazil"
      ],
      "x":"406",
      "y":"1085"
   },
   {
      "name":"sea_23",
      "c_sea":[
         "sea_17",
         "sea_22",
         "sea_27",
         "sea_24"
      ],
      "c_land":[
         "french_equatorial_africa",
         "belgian_congo"
      ],
      "x":"690",
      "y":"1106"
   },
   {
      "name":"sea_24",
      "c_sea":[
         "sea_22",
         "sea_23",
         "sea_27",
         "sea_26",
         "sea_25"
      ],
      "c_land":[
         
      ],
      "x":"498",
      "y":"1212"
   },
   {
      "name":"sea_25",
      "c_sea":[
         "sea_21",
         "sea_22",
         "sea_24",
         "sea_26",
         "sea_43",
         "sea_42"
      ],
      "c_land":[
         
      ],
      "x":"146",
      "y":"1367"
   },
   {
      "name":"sea_26",
      "c_sea":[
         "sea_25",
         "sea_24",
         "sea_27"
      ],
      "c_land":[
         
      ],
      "x":"500",
      "y":"1437"
   },
   {
      "name":"sea_27",
      "c_sea":[
         "sea_26",
         "sea_24",
         "sea_23",
         "sea_28"
      ],
      "c_land":[
         "union_of_south_africa"
      ],
      "x":"790",
      "y":"1387"
   },
   {
      "name":"sea_28",
      "c_sea":[
         "sea_27",
         "sea_33",
         "sea_29"
      ],
      "c_land":[
         "union_of_south_africa",
         "french_madagascar"
      ],
      "x":"985",
      "y":"1444"
   },
   {
      "name":"sea_29",
      "c_sea":[
         "sea_28",
         "sea_32",
         "sea_30"
      ],
      "c_land":[
         "french_madagascar"
      ],
      "x":"1248",
      "y":"1452"
   },
   {
      "name":"sea_30",
      "c_sea":[
         "sea_29",
         "sea_32",
         "sea_31",
         "sea_38",
         "sea_39"
      ],
      "c_land":[
         
      ],
      "x":"1529",
      "y":"1459"
   },
   {
      "name":"sea_31",
      "c_sea":[
         "sea_35",
         "sea_32",
         "sea_30",
         "sea_38",
         "sea_37"
      ],
      "c_land":[
         
      ],
      "x":"1533",
      "y":"1157"
   },
   {
      "name":"sea_32",
      "c_sea":[
         "sea_29",
         "sea_30",
         "sea_31",
         "sea_35",
         "sea_34",
         "sea_33"
      ],
      "c_land":[
         "french_madagascar"
      ],
      "x":"1319",
      "y":"1252"
   },
   {
      "name":"sea_33",
      "c_sea":[
         "sea_32",
         "sea_28",
         "sea_34"
      ],
      "c_land":[
         "french_madagascar",
         "rhodesia"
      ],
      "x":"1106",
      "y":"1222"
   },
   {
      "name":"sea_34",
      "c_sea":[
         "sea_33",
         "sea_32",
         "sea_35"
      ],
      "c_land":[
         "italian_east_africa",
         "persia",
         "trans_jordan",
         "anglo_egypt"
      ],
      "x":"1216",
      "y":"1013"
   },
   {
      "name":"sea_35",
      "c_sea":[
         "sea_34",
         "sea_31",
         "sea_32",
         "sea_36",
         "sea_37"
      ],
      "c_land":[
         "india"
      ],
      "x":"1430",
      "y":"963"
   },
   {
      "name":"sea_36",
      "c_sea":[
         "sea_35",
         "sea_37",
         "sea_48",
         "sea_49",
         "sea_59"
      ],
      "c_land":[
         "french_indochina"
      ],
      "x":"1799",
      "y":"968"
   },
   {
      "name":"sea_37",
      "c_sea":[
         "sea_36",
         "sea_48",
         "sea_35",
         "sea_31",
         "sea_38",
         "sea_47"
      ],
      "c_land":[
         "east_indies"
      ],
      "x":"1688",
      "y":"1145"
   },
   {
      "name":"sea_38",
      "c_sea":[
         "sea_37",
         "sea_31",
         "sea_30",
         "sea_39",
         "sea_46",
         "sea_47"
      ],
      "c_land":[
         "australia"
      ],
      "x":"1875",
      "y":"1272"
   },
   {
      "name":"sea_39",
      "c_sea":[
         "sea_38",
         "sea_30",
         "sea_40"
      ],
      "c_land":[
         "australia"
      ],
      "x":"1860",
      "y":"1463"
   },
   {
      "name":"sea_40",
      "c_sea":[
         "sea_46",
         "sea_39",
         "sea_41"
      ],
      "c_land":[
         "australia"
      ],
      "x":"2249",
      "y":"1434"
   },
   {
      "name":"sea_41",
      "c_sea":[
         "sea_40",
         "sea_46",
         "sea_45",
         "sea_44",
         "sea_42"
      ],
      "c_land":[
         "new_zealand"
      ],
      "x":"2404",
      "y":"1409"
   },
   {
      "name":"sea_42",
      "c_sea":[
         "sea_41",
         "sea_44",
         "sea_43",
         "sea_25"
      ],
      "c_land":[
         
      ],
      "x":"2620",
      "y":"1391"
   },
   {
      "name":"sea_43",
      "c_sea":[
         "sea_44",
         "sea_53",
         "sea_54",
         "sea_42",
         "sea_25",
         "sea_21"
      ],
      "c_land":[
         
      ],
      "x":"2676",
      "y":"1033"
   },
   {
      "name":"sea_44",
      "c_sea":[
         "sea_52",
         "sea_45",
         "sea_41",
         "sea_42",
         "sea_43",
         "sea_53"
      ],
      "c_land":[
         
      ],
      "x":"2507",
      "y":"1089"
   },
   {
      "name":"sea_45",
      "c_sea":[
         "sea_51",
         "sea_50",
         "sea_47",
         "sea_46",
         "sea_41",
         "sea_44",
         "sea_52"
      ],
      "c_land":[
         "solomon_islands"
      ],
      "x":"2320",
      "y":"1169"
   },
   {
      "name":"sea_46",
      "c_sea":[
         "sea_47",
         "sea_38",
         "sea_40",
         "sea_41",
         "sea_45"
      ],
      "c_land":[
         "australia"
      ],
      "x":"2220",
      "y":"1234"
   },
   {
      "name":"sea_47",
      "c_sea":[
         "sea_50",
         "sea_48",
         "sea_37",
         "sea_46",
         "sea_45"
      ],
      "c_land":[
         "new_guinea"
      ],
      "x":"2106",
      "y":"1082"
   },
   {
      "name":"sea_48",
      "c_sea":[
         "sea_49",
         "sea_36",
         "sea_37",
         "sea_47",
         "sea_50"
      ],
      "c_land":[
         "borneo"
      ],
      "x":"1943",
      "y":"1110"
   },
   {
      "name":"sea_49",
      "c_sea":[
         "sea_59",
         "sea_36",
         "sea_48",
         "sea_50",
         "sea_58",
         "sea_60"
      ],
      "c_land":[
         "phillippine_islands"
      ],
      "x":"1963",
      "y":"799"
   },
   {
      "name":"sea_50",
      "c_sea":[
         "sea_58",
         "sea_49",
         "sea_48",
         "sea_47",
         "sea_45",
         "sea_51"
      ],
      "c_land":[
         "caroline_islands"
      ],
      "x":"2121",
      "y":"1512"
   },
   {
      "name":"sea_51",
      "c_sea":[
         "sea_57",
         "sea_60",
         "sea_58",
         "sea_50",
         "sea_45",
         "sea_52"
      ],
      "c_land":[
         "wake_island"
      ],
      "x":"2253",
      "y":"756"
   },
   {
      "name":"sea_52",
      "c_sea":[
         "sea_56",
         "sea_57",
         "sea_51",
         "sea_45",
         "sea_44",
         "sea_53",
         "sea_55"
      ],
      "c_land":[
         "hawaiian_islands"
      ],
      "x":"2426",
      "y":"852"
   },
   {
      "name":"sea_53",
      "c_sea":[
         "sea_55",
         "sea_52",
         "sea_44",
         "sea_43",
         "sea_54"
      ],
      "c_land":[
         
      ],
      "x":"2594",
      "y":"812"
   },
   {
      "name":"sea_54",
      "c_sea":[
         "sea_55",
         "sea_53",
         "sea_43",
		 "sea_20",
		 "sea_21"
      ],
      "c_land":[
         "mexico",
         "western_united_states"
      ],
      "x":"2692",
      "y":"767"
   },
   {
      "name":"sea_55",
      "c_sea":[
         "sea_64",
         "sea_56",
         "sea_52",
         "sea_53",
         "sea_54"
      ],
      "c_land":[
         "western_canada",
         "western_united_states"
      ],
      "x":"2543",
      "y":"489"
   },
   {
      "name":"sea_56",
      "c_sea":[
         "sea_63",
         "sea_57",
         "sea_52",
         "sea_55",
         "sea_64"
      ],
      "c_land":[
         "midway_island"
      ],
      "x":"2414",
      "y":"555"
   },
   {
      "name":"sea_57",
      "c_sea":[
         "sea_63",
         "sea_62",
         "sea_60",
         "sea_51",
         "sea_52",
         "sea_56"
      ],
      "c_land":[
         
      ],
      "x":"2285",
      "y":"554"
   },
   {
      "name":"sea_58",
      "c_sea":[
         "sea_60",
         "sea_49",
         "sea_50",
         "sea_51"
      ],
      "c_land":[
         "okinawa"
      ],
      "x":"2102",
      "y":"758"
   },
   {
      "name":"sea_59",
      "c_sea":[
         "sea_61",
         "sea_60",
         "sea_49",
         "sea_36"
      ],
      "c_land":[
         "kwangtung"
      ],
      "x":"1955",
      "y":"691"
   },
   {
      "name":"sea_60",
      "c_sea":[
         "sea_62",
         "sea_61",
         "sea_59",
         "sea_49",
         "sea_58",
         "sea_51",
         "sea_57"
      ],
      "c_land":[
         "japan",
         "buryatia_ssr"
      ],
      "x":"2161",
      "y":"1512"
   },
   {
      "name":"sea_61",
      "c_sea":[
         "sea_60",
         "sea_59"
      ],
      "c_land":[
         "manchuria",
         "japan"
      ],
      "x":"2052",
      "y":"517"
   },
   {
      "name":"sea_62",
      "c_sea":[
         "sea_63",
         "sea_57",
         "sea_60"
      ],
      "c_land":[
         "soviet_far_east",
         "buryatia_ssr"
      ],
      "x":"2168",
      "y":"277"
   },
   {
      "name":"sea_63",
      "c_sea":[
         "sea_62",
         "sea_57",
         "sea_56",
         "sea_64"
      ],
      "c_land":[
         "alaska",
         "western_canada"
      ],
      "x":"2342",
      "y":"188"
   },
   {
      "name":"sea_64",
      "c_sea":[
         "sea_63",
         "sea_56",
         "sea_55"
      ],
      "c_land":[
         "alaska",
         "western_canada"
      ],
      "x":"2490",
      "y":"333"
   },
   {
      "name":"western_europe",
      "c_sea":[
         "sea_7",
         "sea_13",
		 "sea_6"
      ],
      "c_land":[
         "germany",
         "southern_europe"
      ],
      "x":"650",
      "y":"500"
   },
   {
      "name":"germany",
      "c_sea":[
         "sea_5"
      ],
      "c_land":[
         "western_europe",
         "southern_europe",
		 "eastern_europe",
		 "balkans"
      ],
      "x":"832",
      "y":"442"
   },
]